{"errors":[],"warnings":[],"namedChunkGroups":{"app":{"chunks":[11,0,2],"assets":["webpack-runtime-e0fcd9795462bf90c368.js","webpack-runtime-e0fcd9795462bf90c368.js.map","styles.63815d16896acb63bc46.css","styles-7d16989abf15d132bde6.js","styles-7d16989abf15d132bde6.js.map","app-ddb869cbd336f68b4dcf.js","app-ddb869cbd336f68b4dcf.js.map"],"children":{},"childAssets":{}},"component---src-pages-404-js":{"chunks":[0,1,3],"assets":["styles.63815d16896acb63bc46.css","styles-7d16989abf15d132bde6.js","styles-7d16989abf15d132bde6.js.map","1-bd5cda9b30f3093aec22.js","1-bd5cda9b30f3093aec22.js.map","component---src-pages-404-js-8fd72ad94a7f3d20a33c.js","component---src-pages-404-js-8fd72ad94a7f3d20a33c.js.map"],"children":{},"childAssets":{}},"component---src-pages-about-js":{"chunks":[0,1,13,4],"assets":["styles.63815d16896acb63bc46.css","styles-7d16989abf15d132bde6.js","styles-7d16989abf15d132bde6.js.map","1-bd5cda9b30f3093aec22.js","1-bd5cda9b30f3093aec22.js.map","13-7058625cbe30151c09e2.js","13-7058625cbe30151c09e2.js.map","component---src-pages-about-js-e95257ba1584890a6342.js","component---src-pages-about-js-e95257ba1584890a6342.js.map"],"children":{},"childAssets":{}},"component---src-pages-contacts-js":{"chunks":[0,1,5],"assets":["styles.63815d16896acb63bc46.css","styles-7d16989abf15d132bde6.js","styles-7d16989abf15d132bde6.js.map","1-bd5cda9b30f3093aec22.js","1-bd5cda9b30f3093aec22.js.map","component---src-pages-contacts-js-0bcaffac800cdd7b868f.js","component---src-pages-contacts-js-0bcaffac800cdd7b868f.js.map"],"children":{},"childAssets":{}},"component---src-pages-cooperation-js":{"chunks":[0,1,6],"assets":["styles.63815d16896acb63bc46.css","styles-7d16989abf15d132bde6.js","styles-7d16989abf15d132bde6.js.map","1-bd5cda9b30f3093aec22.js","1-bd5cda9b30f3093aec22.js.map","component---src-pages-cooperation-js-05c99fcfbca553d54e01.js","component---src-pages-cooperation-js-05c99fcfbca553d54e01.js.map"],"children":{},"childAssets":{}},"component---src-pages-index-js":{"chunks":[0,1,7],"assets":["styles.63815d16896acb63bc46.css","styles-7d16989abf15d132bde6.js","styles-7d16989abf15d132bde6.js.map","1-bd5cda9b30f3093aec22.js","1-bd5cda9b30f3093aec22.js.map","component---src-pages-index-js-3335467473115ef30099.js","component---src-pages-index-js-3335467473115ef30099.js.map"],"children":{},"childAssets":{}},"component---src-pages-photos-js":{"chunks":[0,1,8],"assets":["styles.63815d16896acb63bc46.css","styles-7d16989abf15d132bde6.js","styles-7d16989abf15d132bde6.js.map","1-bd5cda9b30f3093aec22.js","1-bd5cda9b30f3093aec22.js.map","component---src-pages-photos-js-69016abd8634a273b796.js","component---src-pages-photos-js-69016abd8634a273b796.js.map"],"children":{},"childAssets":{}},"component---src-pages-reviews-js":{"chunks":[0,1,9],"assets":["styles.63815d16896acb63bc46.css","styles-7d16989abf15d132bde6.js","styles-7d16989abf15d132bde6.js.map","1-bd5cda9b30f3093aec22.js","1-bd5cda9b30f3093aec22.js.map","component---src-pages-reviews-js-a804f5d195fd1f10edee.js","component---src-pages-reviews-js-a804f5d195fd1f10edee.js.map"],"children":{},"childAssets":{}},"component---src-pages-videos-js":{"chunks":[0,1,12,10],"assets":["styles.63815d16896acb63bc46.css","styles-7d16989abf15d132bde6.js","styles-7d16989abf15d132bde6.js.map","1-bd5cda9b30f3093aec22.js","1-bd5cda9b30f3093aec22.js.map","12-6133911ba62b17d50734.js","12-6133911ba62b17d50734.js.map","component---src-pages-videos-js-32b20fd32e377186ac9f.js","component---src-pages-videos-js-32b20fd32e377186ac9f.js.map"],"children":{},"childAssets":{}}},"assetsByChunkName":{"app":["webpack-runtime-e0fcd9795462bf90c368.js","styles.63815d16896acb63bc46.css","styles-7d16989abf15d132bde6.js","app-ddb869cbd336f68b4dcf.js"],"component---src-pages-404-js":["styles.63815d16896acb63bc46.css","styles-7d16989abf15d132bde6.js","1-bd5cda9b30f3093aec22.js","component---src-pages-404-js-8fd72ad94a7f3d20a33c.js"],"component---src-pages-about-js":["styles.63815d16896acb63bc46.css","styles-7d16989abf15d132bde6.js","1-bd5cda9b30f3093aec22.js","13-7058625cbe30151c09e2.js","component---src-pages-about-js-e95257ba1584890a6342.js"],"component---src-pages-contacts-js":["styles.63815d16896acb63bc46.css","styles-7d16989abf15d132bde6.js","1-bd5cda9b30f3093aec22.js","component---src-pages-contacts-js-0bcaffac800cdd7b868f.js"],"component---src-pages-cooperation-js":["styles.63815d16896acb63bc46.css","styles-7d16989abf15d132bde6.js","1-bd5cda9b30f3093aec22.js","component---src-pages-cooperation-js-05c99fcfbca553d54e01.js"],"component---src-pages-index-js":["styles.63815d16896acb63bc46.css","styles-7d16989abf15d132bde6.js","1-bd5cda9b30f3093aec22.js","component---src-pages-index-js-3335467473115ef30099.js"],"component---src-pages-photos-js":["styles.63815d16896acb63bc46.css","styles-7d16989abf15d132bde6.js","1-bd5cda9b30f3093aec22.js","component---src-pages-photos-js-69016abd8634a273b796.js"],"component---src-pages-reviews-js":["styles.63815d16896acb63bc46.css","styles-7d16989abf15d132bde6.js","1-bd5cda9b30f3093aec22.js","component---src-pages-reviews-js-a804f5d195fd1f10edee.js"],"component---src-pages-videos-js":["styles.63815d16896acb63bc46.css","styles-7d16989abf15d132bde6.js","1-bd5cda9b30f3093aec22.js","12-6133911ba62b17d50734.js","component---src-pages-videos-js-32b20fd32e377186ac9f.js"]}}